Makefile
bootstrap.py
buildout-5.0.cfg
buildout-plone5.cfg
buildout.cfg
setup.cfg
setup.py
docs/Makefile
docs/make.bat
docs/source/HISTORY.rst
docs/source/README.rst
docs/source/conf.py
docs/source/content-types.rst
docs/source/index.rst
docs/source/installation.rst
docs/source/integration-ploneformgen.rst
docs/source/resource-directories.rst
pp/__init__.py
pp.client_plone.egg-info/PKG-INFO
pp.client_plone.egg-info/SOURCES.txt
pp.client_plone.egg-info/dependency_links.txt
pp.client_plone.egg-info/entry_points.txt
pp.client_plone.egg-info/namespace_packages.txt
pp.client_plone.egg-info/not-zip-safe
pp.client_plone.egg-info/requires.txt
pp.client_plone.egg-info/top_level.txt
pp/client/__init__.py
pp/client/plone/__init__.py
pp/client/plone/configure.zcml
pp/client/plone/header.txt
pp/client/plone/i18n.py
pp/client/plone/interfaces.py
pp/client/plone/logger.py
pp/client/plone/meta.zcml
pp/client/plone/zcml.py
pp/client/plone/browser/__init__.py
pp/client/plone/browser/compatible.py
pp/client/plone/browser/configure.zcml
pp/client/plone/browser/controlpanel.py
pp/client/plone/browser/demo.py
pp/client/plone/browser/docx_import.pt
pp/client/plone/browser/docx_importer.py
pp/client/plone/browser/docx_view.pt
pp/client/plone/browser/images.py
pp/client/plone/browser/pdf.py
pp/client/plone/browser/preflight.pt
pp/client/plone/browser/sorting.py
pp/client/plone/browser/splitter.py
pp/client/plone/browser/transformations.py
pp/client/plone/browser/util.py
pp/client/plone/browser/resources/local.js
pp/client/plone/browser/resources/styles.css
pp/client/plone/browser/tests/__init__.py
pp/client/plone/browser/types/__init__.py
pp/client/plone/browser/types/dexterity.pt
pp/client/plone/browser/types/dexterity.py
pp/client/plone/browser/types/document.pt
pp/client/plone/browser/types/document.py
pp/client/plone/browser/types/folder.py
pp/client/plone/browser/types/folder_flat.py
pp/client/plone/browser/types/folder_nested.py
pp/client/plone/browser/types/glossary.pt
pp/client/plone/browser/types/glossary.py
pp/client/plone/browser/types/image.pt
pp/client/plone/browser/types/image.py
pp/client/plone/browser/types/newsitem.pt
pp/client/plone/browser/types/newsitem.py
pp/client/plone/browser/types/pfg.py
pp/client/plone/browser/types/topic.py
pp/client/plone/extender/__init__.py
