Metadata-Version: 1.1
Name: pp.client-plone
Version: 0.4.7
Summary: Produce & Publisher Plone Client Connector
Home-page: http://pypi.python.org/pypi/pp.client-plone
Author: Andreas Jung
Author-email: info@zopyx.com
License: GPL
Keywords: PDF Plone Python EBook EPUB
Platform: UNKNOWN
Classifier: Programming Language :: Python
Classifier: Framework :: Plone
Classifier: Framework :: Plone :: 4.3
Classifier: Framework :: Plone :: 5.0
Classifier: Framework :: Plone :: 5.1
Classifier: Framework :: Zope2
Classifier: Topic :: Software Development :: Libraries :: Python Modules
